standup_shows/__init__.py
standup_shows/models.py
standup_shows/standup.py
standup_shows-1.0.1.dist-info/entry_points.txt
standup_shows-1.0.1.dist-info/LICENSE
standup_shows-1.0.1.dist-info/WHEEL
standup_shows-1.0.1.dist-info/METADATA
standup_shows-1.0.1.dist-info/RECORD
