Metadata-Version: 2.1
Name: standup-shows
Version: 1.0.1
Summary: Find stand-up comedy shows near you from the command line.
Home-page: https://github.com/calwarhurst/standup-shows
License: GPL-3.0-or-later
Author: Cal Warhurst
Requires-Python: >=3.9,<4.0
Classifier: License :: OSI Approved :: GNU General Public License v3 (GPLv3)
Classifier: License :: OSI Approved :: GNU General Public License v3 or later (GPLv3+)
Classifier: Operating System :: OS Independent
Classifier: Programming Language :: Python :: 3
Classifier: Programming Language :: Python :: 3.10
Classifier: Programming Language :: Python :: 3.9
Requires-Dist: beautifulsoup4
Requires-Dist: fire
Requires-Dist: requests
Project-URL: Repository, https://github.com/calwarhurst/standup-shows
